<?xml version='1.0' encoding='utf-8'?>
<items><item><status>В наличии</status><cae>3151009</cae><price_novosib3>4285</price_novosib3><price_novosib3_rozn>5006</price_novosib3_rozn><price_nvkz2>4285</price_nvkz2><price_nvkz2_rozn>5006</price_nvkz2_rozn><price_yamka>4285</price_yamka><price_yamka_rozn>5006</price_yamka_rozn><rest_novosib3>30</rest_novosib3><rest_nvkz2>более 40</rest_nvkz2><rest_yamka>более 40</rest_yamka><gtin>04604278002757, 02900043220176, 02900062335882, 04650282304752</gtin><brand>Viatti</brand><model>Brina Nordico V-522</model><width>185</width><height>65</height><diameter>R15</diameter><load_index>88</load_index><speed_index>T</speed_index><season>Зимняя</season><tiretype>Легковая</tiretype><diametr_out>0</diametr_out><thorn>Да</thorn><img_small>https://api-b2b.pwrs.ru/27986/pictures/tyres/Viatti/Brina_Nordico_V-522/src/big_1.jpg</img_small><name>185/65R15 88T Brina Nordico V-522 TL (шип.)</name><design>R</design><brand_info>https://www.4tochki.ru/descriptions/brands/viatti/info.html</brand_info><model_info>https://www.4tochki.ru/descriptions/models/viatti/Brina_Nordico_V-522/info.html</model_info></item><item><status>В наличии</status><cae>3151014</cae><price_novosib3>5279</price_novosib3><price_novosib3_rozn>6167</price_novosib3_rozn><price_nvkz2>5279</price_nvkz2><price_nvkz2_rozn>6167</price_nvkz2_rozn><price_tomsk>5279</price_tomsk><price_tomsk_rozn>6167</price_tomsk_rozn><price_yamka>5279</price_yamka><price_yamka_rozn>6167</price_yamka_rozn><rest_novosib3>7</rest_novosib3><rest_nvkz2>5</rest_nvkz2><rest_tomsk>4</rest_tomsk><rest_yamka>34</rest_yamka><gtin>04604278002894, 02900055618442</gtin><brand>Viatti</brand><model>Brina Nordico V-522</model><width>205</width><height>65</height><diameter>R15</diameter><load_index>94</load_index><speed_index>T</speed_index><season>Зимняя</season><tiretype>Легковая</tiretype><diametr_out>0</diametr_out><thorn>Да</thorn><img_small>https://api-b2b.pwrs.ru/27986/pictures/tyres/Viatti/Brina_Nordico_V-522/src/big_1.jpg</img_small><name>205/65R15 94T Brina Nordico V-522 TL (шип.)</name><design>R</design><brand_info>https://www.4tochki.ru/descriptions/brands/viatti/info.html</brand_info><model_info>https://www.4tochki.ru/descriptions/models/viatti/Brina_Nordico_V-522/info.html</model_info></item><item><status>В наличии</status><cae>T429605</cae><price_novosib3>10271</price_novosib3><price_novosib3_rozn>12640</price_novosib3_rozn><rest_novosib3>3</rest_novosib3><gtin>02900062518407, 02900042526620, 02900012023098, 06419440161914</gtin><brand>Nokian Tyres</brand><model>Nordman RS2 SUV</model><width>235</width><height>55</height><diameter>R18</diameter><load_index>104</load_index><speed_index>R</speed_index><season>Зимняя</season><tiretype>Легковая</tiretype><diametr_out>0</diametr_out><tonnage>Да</tonnage><img_small>https://api-b2b.pwrs.ru/27986/pictures/tyres/Nokian_Tyres/Nordman_RS2_SUV/src/big_0.png</img_small><name>235/55R18 104R XL Nordman RS2 SUV TL</name><design>R</design><brand_info>https://www.4tochki.ru/descriptions/brands/nokian/info.html</brand_info><model_info>https://www.4tochki.ru/descriptions/models/nokian/Nordman_RS2_SUV/info.html</model_info></item><item><status>В наличии</status><cae>T429610</cae><price_novosib3>9408</price_novosib3><price_novosib3_rozn>11580</price_novosib3_rozn><rest_novosib3>1</rest_novosib3><gtin>02900036627319, 06419440161839, 02900012023180</gtin><brand>Nokian Tyres</brand><model>Nordman RS2 SUV</model><width>225</width><height>70</height><diameter>R16</diameter><load_index>107</load_index><speed_index>R</speed_index><season>Зимняя</season><tiretype>Легковая</tiretype><diametr_out>0</diametr_out><tonnage>Да</tonnage><img_small>https://api-b2b.pwrs.ru/27986/pictures/tyres/Nokian_Tyres/Nordman_RS2_SUV/src/big_0.png</img_small><name>225/70R16 107R XL Nordman RS2 SUV TL</name><design>R</design><brand_info>https://www.4tochki.ru/descriptions/brands/nokian/info.html</brand_info><model_info>https://www.4tochki.ru/descriptions/models/nokian/Nordman_RS2_SUV/info.html</model_info></item><item><status>В наличии</status><cae>0347105</cae><price_novosib3>11772</price_novosib3><price_novosib3_rozn>14480</price_novosib3_rozn><rest_novosib3>4</rest_novosib3><gtin>04019238661507</gtin><brand>Continental</brand><model>IceContact 2 SUV</model><width>235</width><height>70</height><diameter>R16</diameter><load_index>106</load_index><speed_index>T</speed_index><season>Зимняя</season><tiretype>Легковая</tiretype><diametr_out>0</diametr_out><thorn>Да</thorn><thorn_type>KD</thorn_type><protection>FR</protection><img_small>https://api-b2b.pwrs.ru/27986/pictures/tyres/Continental/IceContact_2_SUV/src/big_1.png</img_small><name>235/70R16 106T IceContact 2 SUV TL FR KD (шип.)</name><design>R</design><brand_info>https://www.4tochki.ru/descriptions/brands/continental/info.html</brand_info><model_info>https://www.4tochki.ru/descriptions/models/continental/IceContact_2_SUV/info.html</model_info></item><item><status>В наличии</status><cae>4377900</cae><price_novosib3>9182</price_novosib3><price_novosib3_rozn>11300</price_novosib3_rozn><price_nvkz2>9182</price_nvkz2><price_nvkz2_rozn>11300</price_nvkz2_rozn><price_tomsk>9182</price_tomsk><price_tomsk_rozn>11300</price_tomsk_rozn><rest_novosib3>8</rest_novosib3><rest_nvkz2>4</rest_nvkz2><rest_tomsk>4</rest_tomsk><gtin>08019227255669, 08019227376326, 08019227437799, 02900018016681, 02900061416797</gtin><brand>Pirelli</brand><model>Ice Zero FR</model><width>225</width><height>55</height><diameter>R17</diameter><load_index>101</load_index><speed_index>H</speed_index><season>Зимняя</season><tiretype>Легковая</tiretype><diametr_out>0</diametr_out><tonnage>Да</tonnage><img_small>https://api-b2b.pwrs.ru/27986/pictures/tyres/Pirelli/Ice_Zero_FR/src/big_0.png</img_small><name>225/55R17 101H XL Ice Zero FR TL</name><design>R</design><brand_info>https://www.4tochki.ru/descriptions/brands/pirelli/info.html</brand_info><model_info>https://www.4tochki.ru/descriptions/models/pirelli/IceZero_FR/info.html</model_info></item><item><status>В наличии</status><cae>3151034</cae><price_novosib3>6004</price_novosib3><price_novosib3_rozn>7014</price_novosib3_rozn><price_nvkz2>6004</price_nvkz2><price_nvkz2_rozn>7014</price_nvkz2_rozn><price_tomsk>6004</price_tomsk><price_tomsk_rozn>7014</price_tomsk_rozn><rest_novosib3>38</rest_novosib3><rest_nvkz2>39</rest_nvkz2><rest_tomsk>18</rest_tomsk><gtin>02900062795136, 04604278002207, 02900053152573, 02900024335578, 04670122566614</gtin><brand>Viatti</brand><model>Bosco Nordico V-523</model><width>215</width><height>65</height><diameter>R16</diameter><load_index>98</load_index><speed_index>T</speed_index><season>Зимняя</season><tiretype>Легковая</tiretype><diametr_out>0</diametr_out><thorn>Да</thorn><img_small>https://api-b2b.pwrs.ru/27986/pictures/tyres/Viatti/Bosco_Nordico_V-523/src/big_1.jpg</img_small><name>215/65R16 98T Bosco Nordico V-523 TL (шип.)</name><design>R</design><brand_info>https://www.4tochki.ru/descriptions/brands/viatti/info.html</brand_info><model_info>https://www.4tochki.ru/descriptions/models/viatti/Bosco_Nordico_V-523 /info.html</model_info></item><item><status>В наличии</status><cae>4384700</cae><price_novosib3>17310</price_novosib3><price_novosib3_rozn>21300</price_novosib3_rozn><price_nvkz2>17310</price_nvkz2><price_nvkz2_rozn>21300</price_nvkz2_rozn><price_tomsk>17310</price_tomsk><price_tomsk_rozn>21300</price_tomsk_rozn><rest_novosib3>15</rest_novosib3><rest_nvkz2>4</rest_nvkz2><rest_tomsk>20</rest_tomsk><gtin>02900060142147, 08019227271850, 08019227438475, 02900012014560</gtin><brand>Pirelli</brand><model>Ice Zero</model><width>265</width><height>50</height><diameter>R20</diameter><load_index>111</load_index><speed_index>H</speed_index><season>Зимняя</season><tiretype>Легковая</tiretype><diametr_out>0</diametr_out><thorn>Да</thorn><tonnage>Да</tonnage><img_small>https://api-b2b.pwrs.ru/27986/pictures/tyres/Pirelli/Ice_Zero/src/big_1.png</img_small><name>265/50R20 111H XL Ice Zero TL (шип.)</name><design>R</design><brand_info>https://www.4tochki.ru/descriptions/brands/pirelli/info.html</brand_info><model_info>https://www.4tochki.ru/descriptions/models/pirelli/Winter_Ice_Zero/info.html</model_info></item><item><status>В наличии</status><cae>R1584</cae><price_novosib3>11184</price_novosib3><price_novosib3_rozn>13690</price_novosib3_rozn><price_nvkz2>11184</price_nvkz2><price_nvkz2_rozn>13690</price_nvkz2_rozn><price_tomsk>11184</price_tomsk><price_tomsk_rozn>13690</price_tomsk_rozn><price_dvdv>11184</price_dvdv><price_dvdv_rozn>13690</price_dvdv_rozn><price_yamka>11184</price_yamka><price_yamka_rozn>13690</price_yamka_rozn><rest_novosib3>более 40</rest_novosib3><rest_nvkz2>12</rest_nvkz2><rest_tomsk>4</rest_tomsk><rest_dvdv>более 40</rest_dvdv><rest_yamka>33</rest_yamka><gtin>04968814910488, 02900021168919, 02900053498749, 02900011973639, 02900063069113</gtin><brand>Yokohama</brand><model>iceGuard Studless G075</model><width>235</width><height>65</height><diameter>R17</diameter><load_index>108</load_index><speed_index>Q</speed_index><season>Зимняя</season><tiretype>Легковая</tiretype><diametr_out>0</diametr_out><tonnage>Да</tonnage><img_small>https://api-b2b.pwrs.ru/27986/pictures/tyres/Yokohama/iceGuard_Studless_G075/src/big_0.png</img_small><name>235/65R17 108Q XL iceGuard Studless G075 TL</name><design>R</design><brand_info>https://www.4tochki.ru/descriptions/brands/yokohama/info.html</brand_info><model_info>https://www.4tochki.ru/descriptions/models/yokohama/iceGuard_Studless_G075/info.html</model_info></item><item><status>В наличии</status><cae>R1013</cae><price_novosib3>9397</price_novosib3><price_novosib3_rozn>11720</price_novosib3_rozn><price_oh_zabpet>9397</price_oh_zabpet><price_oh_zabpet_rozn>11720</price_oh_zabpet_rozn><price_oh_nsibir>9397</price_oh_nsibir><price_oh_nsibir_rozn>11720</price_oh_nsibir_rozn><price_oh_nvsbrus>9397</price_oh_nvsbrus><price_oh_nvsbrus_rozn>11720</price_oh_nvsbrus_rozn><price_oh_nsovets>9397</price_oh_nsovets><price_oh_nsovets_rozn>11720</price_oh_nsovets_rozn><price_nvkz2>9397</price_nvkz2><price_nvkz2_rozn>11720</price_nvkz2_rozn><price_tomsk>9397</price_tomsk><price_tomsk_rozn>11720</price_tomsk_rozn><price_yamka>9397</price_yamka><price_yamka_rozn>11720</price_yamka_rozn><rest_novosib3>более 40</rest_novosib3><rest_oh_zabpet>4</rest_oh_zabpet><rest_oh_nsibir>4</rest_oh_nsibir><rest_oh_nvsbrus>4</rest_oh_nvsbrus><rest_oh_nsovets>4</rest_oh_nsovets><rest_nvkz2>16</rest_nvkz2><rest_tomsk>16</rest_tomsk><rest_yamka>более 40</rest_yamka><gtin>04968814902384, 02900309858969, 02900012042969, 02900285131698</gtin><brand>Yokohama</brand><model>BluEarth E70BZ</model><width>215</width><height>55</height><diameter>R17</diameter><load_index>94</load_index><speed_index>V</speed_index><season>Летняя</season><tiretype>Легковая</tiretype><diametr_out>0</diametr_out><img_small>https://api-b2b.pwrs.ru/27986/pictures/tyres/Yokohama/BluEarth_E70_BZ/src/big_0.png</img_small><name>215/55R17 94V BluEarth E70BZ TL</name><design>R</design><brand_info>https://www.4tochki.ru/descriptions/brands/yokohama/info.html</brand_info><model_info>https://www.4tochki.ru/descriptions/models/yokohama/BluEarth_E70_BZ/info.html</model_info></item><item><status>В наличии</status><cae>R1155</cae><price_novosib3>12043</price_novosib3><price_novosib3_rozn>15020</price_novosib3_rozn><price_oh_nvsbrus>12043</price_oh_nvsbrus><price_oh_nvsbrus_rozn>15020</price_oh_nvsbrus_rozn><price_tomsk>12043</price_tomsk><price_tomsk_rozn>15020</price_tomsk_rozn><price_yamka>12043</price_yamka><price_yamka_rozn>15020</price_yamka_rozn><rest_novosib3>5</rest_novosib3><rest_oh_nvsbrus>4</rest_oh_nvsbrus><rest_tomsk>12</rest_tomsk><rest_yamka>34</rest_yamka><gtin>04968814904227, 02900235321308, 02900014584467, 02900277398429</gtin><brand>Yokohama</brand><model>Geolandar A/T G015</model><width>275</width><height>70</height><diameter>R16</diameter><load_index>114</load_index><speed_index>H</speed_index><season>Всесезонная</season><tiretype>Легковая</tiretype><diametr_out>0</diametr_out><side>M+S 3PMSF</side><img_small>https://api-b2b.pwrs.ru/27986/pictures/tyres/Yokohama/Geolandar_A_T_G015/src/big_0.png</img_small><name>275/70R16 114H Geolandar A/T G015 TL M+S 3PMSF</name><design>R</design><brand_info>https://www.4tochki.ru/descriptions/brands/yokohama/info.html</brand_info><model_info>https://www.4tochki.ru/descriptions/models/yokohama/Geolandar_AT_G015/info.html</model_info></item><item><status>В наличии</status><cae>2744600</cae><price_novosib3>11697</price_novosib3><price_novosib3_rozn>14630</price_novosib3_rozn><price_nvkz2>11697</price_nvkz2><price_nvkz2_rozn>14630</price_nvkz2_rozn><rest_novosib3>18</rest_novosib3><rest_nvkz2>4</rest_nvkz2><gtin>02900011997819, 02900074815761, 08019227274462, 02900249027203</gtin><brand>Pirelli</brand><model>Scorpion Verde</model><width>235</width><height>55</height><diameter>R18</diameter><load_index>100</load_index><speed_index>V</speed_index><season>Летняя</season><tiretype>Легковая</tiretype><diametr_out>0</diametr_out><omolog>K1</omolog><img_small>https://api-b2b.pwrs.ru/27986/pictures/tyres/Pirelli/Scorpion_Verde/src/big_0.png</img_small><name>235/55R18 100V Scorpion Verde K1 TL</name><design>R</design><brand_info>https://www.4tochki.ru/descriptions/brands/pirelli/info.html</brand_info><model_info>https://www.4tochki.ru/descriptions/models/pirelli/Scorpion_Verde/info.html</model_info></item><item><status>В наличии</status><cae>R3044</cae><price_novosib3>12105</price_novosib3><price_novosib3_rozn>14820</price_novosib3_rozn><price_nvkz2>12105</price_nvkz2><price_nvkz2_rozn>14820</price_nvkz2_rozn><price_tomsk>12105</price_tomsk><price_tomsk_rozn>14820</price_tomsk_rozn><rest_novosib3>более 40</rest_novosib3><rest_nvkz2>более 40</rest_nvkz2><rest_tomsk>12</rest_tomsk><gtin>02900012387480, 02900028935019, 02900020924271, 02900072360485, 04968814933432, 02900009793737, 02900018016704, 02900018032551</gtin><brand>Yokohama</brand><model>iceGuard Stud iG65</model><width>215</width><height>60</height><diameter>R17</diameter><load_index>100</load_index><speed_index>T</speed_index><season>Зимняя</season><tiretype>Легковая</tiretype><diametr_out>0</diametr_out><thorn>Да</thorn><tonnage>Да</tonnage><img_small>https://api-b2b.pwrs.ru/27986/pictures/tyres/Yokohama/iceGuard_Stud_iG65/src/big_1.png</img_small><name>215/60R17 100T XL iceGuard Stud iG65 TL (шип.)</name><design>R</design><brand_info>https://www.4tochki.ru/descriptions/brands/yokohama/info.html</brand_info><model_info>https://www.4tochki.ru/descriptions/models/yokohama/iceGuard_Stud_iG65/info.html</model_info></item><item><status>В наличии</status><cae>R3053</cae><price_novosib3>13757</price_novosib3><price_novosib3_rozn>16840</price_novosib3_rozn><price_nvkz2>13757</price_nvkz2><price_nvkz2_rozn>16840</price_nvkz2_rozn><price_yamka>13757</price_yamka><price_yamka_rozn>16840</price_yamka_rozn><rest_novosib3>более 40</rest_novosib3><rest_nvkz2>4</rest_nvkz2><rest_yamka>более 40</rest_yamka><gtin>02900055929272, 04650223834331, 04968814933524, 02900014170349, 02900497793240</gtin><brand>Yokohama</brand><model>iceGuard Stud iG65</model><width>225</width><height>60</height><diameter>R18</diameter><load_index>104</load_index><speed_index>T</speed_index><season>Зимняя</season><tiretype>Легковая</tiretype><diametr_out>0</diametr_out><thorn>Да</thorn><tonnage>Да</tonnage><img_small>https://api-b2b.pwrs.ru/27986/pictures/tyres/Yokohama/iceGuard_Stud_iG65/src/big_1.png</img_small><name>225/60R18 104T XL iceGuard Stud iG65 TL (шип.)</name><design>R</design><brand_info>https://www.4tochki.ru/descriptions/brands/yokohama/info.html</brand_info><model_info>https://www.4tochki.ru/descriptions/models/yokohama/iceGuard_Stud_iG65/info.html</model_info></item><item><status>В наличии</status><cae>0348164</cae><price_novosib3>6650</price_novosib3><price_novosib3_rozn>7910</price_novosib3_rozn><rest_novosib3>4</rest_novosib3><gtin>04024064740630, 02900018699617, 02900078488893</gtin><brand>Gislaved</brand><model>Soft Frost 200</model><width>215</width><height>55</height><diameter>R16</diameter><load_index>97</load_index><speed_index>T</speed_index><season>Зимняя</season><tiretype>Легковая</tiretype><diametr_out>0</diametr_out><tonnage>Да</tonnage><img_small>https://api-b2b.pwrs.ru/27986/pictures/tyres/Gislaved/Soft_Frost_200/src/big_0.png</img_small><name>215/55R16 97T XL Soft Frost 200 TL</name><design>R</design><brand_info>https://www.4tochki.ru/descriptions/brands/gislaved/info.html</brand_info><model_info>https://www.4tochki.ru/descriptions/models/gislaved/Soft*Frost_200/info.html</model_info></item><item><status>В наличии</status><cae>504069</cae><price_novosib3>22650</price_novosib3><price_novosib3_rozn>29840</price_novosib3_rozn><price_yamka>22650</price_yamka><price_yamka_rozn>29840</price_yamka_rozn><rest_novosib3>1</rest_novosib3><rest_yamka>более 40</rest_yamka><gtin>03528705040697, 04810958123364, 02900272378136, 02900012003625</gtin><brand>Michelin</brand><model>Pilot Sport 4</model><width>225</width><height>45</height><diameter>R18</diameter><load_index>95</load_index><speed_index>Y</speed_index><season>Летняя</season><tiretype>Легковая</tiretype><diametr_out>0</diametr_out><tonnage>Да</tonnage><runflat>Да</runflat><omolog>*</omolog><img_small>https://api-b2b.pwrs.ru/27986/pictures/tyres/Michelin/Pilot_Sport_4/src/big_0.png</img_small><name>225/45R18 95Y XL Pilot Sport 4 * TL ZP</name><design>R</design><brand_info>https://www.4tochki.ru/descriptions/brands/michelin/info.html</brand_info><model_info>https://www.4tochki.ru/descriptions/models/michelin/Pilot_Sport_PS4/info.html</model_info></item><item><status>В наличии</status><cae>470472</cae><price_novosib3>26945</price_novosib3><price_novosib3_rozn>33140</price_novosib3_rozn><price_sk2>29243</price_sk2><price_sk2_rozn>35834</price_sk2_rozn><price_yamka>26945</price_yamka><price_yamka_rozn>33140</price_yamka_rozn><rest_novosib3>4</rest_novosib3><rest_sk2>30</rest_sk2><rest_yamka>17</rest_yamka><gtin>02900056387774, 04650282470396, 02900014234300, 03528704704729</gtin><brand>Michelin</brand><model>X-Ice North 4 SUV</model><width>235</width><height>65</height><diameter>R18</diameter><load_index>110</load_index><speed_index>T</speed_index><season>Зимняя</season><tiretype>Легковая</tiretype><diametr_out>0</diametr_out><thorn>Да</thorn><tonnage>Да</tonnage><img_small>https://api-b2b.pwrs.ru/27986/pictures/tyres/Michelin/X-Ice_North_4_SUV/src/big_1.png</img_small><name>235/65R18 110T XL X-Ice North 4 SUV TL (шип.)</name><design>R</design><brand_info>https://www.4tochki.ru/descriptions/brands/michelin/info.html</brand_info><model_info>https://www.4tochki.ru/descriptions/models/michelin/X-Ice_North_4_SUV/info.html</model_info></item><item><status>В наличии</status><cae>R4655</cae><price_novosib3>24175</price_novosib3><price_novosib3_rozn>29690</price_novosib3_rozn><price_yamka>24175</price_yamka><price_yamka_rozn>29690</price_yamka_rozn><rest_novosib3>4</rest_novosib3><rest_yamka>6</rest_yamka><gtin>04968814964085, 02900022106873</gtin><brand>Yokohama</brand><model>iceGuard Studless iG60A</model><width>245</width><height>40</height><diameter>R20</diameter><load_index>95</load_index><speed_index>Q</speed_index><season>Зимняя</season><tiretype>Легковая</tiretype><diametr_out>0</diametr_out><img_small>https://api-b2b.pwrs.ru/27986/pictures/tyres/Yokohama/iceGuard_Studless_iG60A/src/big_0.png</img_small><name>245/40R20 95Q iceGuard Studless iG60A TL</name><design>R</design><brand_info>https://www.4tochki.ru/descriptions/brands/yokohama/info.html</brand_info><model_info>https://www.4tochki.ru/descriptions/models/yokohama/iceGuard_Studless_iG60A/info.html</model_info></item><item><status>В наличии</status><cae>557303</cae><price_novosib3>31877</price_novosib3><price_novosib3_rozn>39060</price_novosib3_rozn><rest_novosib3>1</rest_novosib3><gtin>03528705573034, 02900058048437</gtin><brand>Michelin</brand><model>X-Ice Snow SUV</model><width>255</width><height>55</height><diameter>R19</diameter><load_index>111</load_index><speed_index>T</speed_index><season>Зимняя</season><tiretype>Легковая</tiretype><diametr_out>0</diametr_out><tonnage>Да</tonnage><img_small>https://api-b2b.pwrs.ru/27986/pictures/tyres/Michelin/X-Ice_Snow_SUV/src/big_0.png</img_small><name>255/55R19 111T XL X-Ice Snow SUV TL</name><design>R</design><brand_info>https://www.4tochki.ru/descriptions/brands/michelin/info.html</brand_info><model_info>https://www.4tochki.ru/descriptions/models/michelin/X-Ice_Snow_SUV/info.html</model_info></item><item><status>В наличии</status><cae>R7476</cae><price_novosib3>13447</price_novosib3><price_novosib3_rozn>16460</price_novosib3_rozn><price_nvkz2>13447</price_nvkz2><price_nvkz2_rozn>16460</price_nvkz2_rozn><price_tomsk>13447</price_tomsk><price_tomsk_rozn>16460</price_tomsk_rozn><price_yamka>13447</price_yamka><price_yamka_rozn>16460</price_yamka_rozn><rest_novosib3>8</rest_novosib3><rest_nvkz2>7</rest_nvkz2><rest_tomsk>23</rest_tomsk><rest_yamka>более 40</rest_yamka><gtin>04548515026482, 02900086847187, 02900062264885</gtin><brand>Yokohama</brand><model>iceGuard Stud iG65</model><width>245</width><height>70</height><diameter>R16</diameter><load_index>111</load_index><speed_index>T</speed_index><season>Зимняя</season><tiretype>Легковая</tiretype><diametr_out>0</diametr_out><thorn>Да</thorn><img_small>https://api-b2b.pwrs.ru/27986/pictures/tyres/Yokohama/iceGuard_Stud_iG65/src/big_1.png</img_small><name>245/70R16 111T iceGuard Stud iG65 TL (шип.)</name><design>R</design><brand_info>https://www.4tochki.ru/descriptions/brands/yokohama/info.html</brand_info><model_info>https://www.4tochki.ru/descriptions/models/yokohama/iceGuard_Stud_iG65/info.html</model_info></item><item><status>В наличии</status><cae>5805300</cae><price_novosib3>16196</price_novosib3><price_novosib3_rozn>20250</price_novosib3_rozn><price_sk3>16196</price_sk3><price_sk3_rozn>20250</price_sk3_rozn><price_yamka>16196</price_yamka><price_yamka_rozn>20250</price_yamka_rozn><rest_novosib3>8</rest_novosib3><rest_sk3>более 40</rest_sk3><rest_yamka>5</rest_yamka><gtin>02900074542094, 02900077049552, 08019227363050, 08019227580532</gtin><brand>Pirelli</brand><model>Scorpion</model><width>255</width><height>45</height><diameter>R19</diameter><load_index>100</load_index><speed_index>V</speed_index><season>Летняя</season><tiretype>Легковая</tiretype><diametr_out>0</diametr_out><img_small>https://api-b2b.pwrs.ru/27986/pictures/tyres/Pirelli/Scorpion/src/big_0.png</img_small><name>255/45R19 100V Scorpion TL</name><design>R</design><brand_info>https://www.4tochki.ru/descriptions/brands/pirelli/info.html</brand_info><model_info>https://www.4tochki.ru/descriptions/models/pirelli/Scorpion/info.html</model_info></item><item><status>В наличии</status><cae>3220012622</cae><price_novosib3>5880</price_novosib3><price_novosib3_rozn>6880</price_novosib3_rozn><rest_novosib3>4</rest_novosib3><gtin>02900074542155, 06959655481259, 02900296640226</gtin><brand>Sailun</brand><model>Atrezzo Elite</model><width>215</width><height>45</height><diameter>R16</diameter><load_index>90</load_index><speed_index>V</speed_index><season>Летняя</season><tiretype>Легковая</tiretype><diametr_out>0</diametr_out><tonnage>Да</tonnage><img_small>https://api-b2b.pwrs.ru/27986/pictures/tyres/Sailun/Atrezzo_Elite/src/big_0.png</img_small><name>215/45R16 90V XL Atrezzo Elite TL</name><design>R</design><brand_info>https://www.4tochki.ru/descriptions/brands/Sailun/info.html</brand_info><model_info>https://www.4tochki.ru/descriptions/models/sailun/AtrezzoElite/info.html</model_info></item><item><status>В наличии</status><cae>3220012086</cae><price_novosib3>6909</price_novosib3><price_novosib3_rozn>8090</price_novosib3_rozn><rest_novosib3>11</rest_novosib3><gtin>06959655477498, 06959655443608, 02900075280957</gtin><brand>Sailun</brand><model>Ice Blazer Alpine Evo 1</model><width>255</width><height>40</height><diameter>R19</diameter><load_index>100</load_index><speed_index>V</speed_index><season>Зимняя</season><tiretype>Легковая</tiretype><diametr_out>0</diametr_out><tonnage>Да</tonnage><img_small>https://api-b2b.pwrs.ru/27986/pictures/tyres/Sailun/Ice_Blazer_Alpine_Evo_1/src/big_0.png</img_small><name>255/40R19 100V XL Ice Blazer Alpine Evo 1 TL</name><design>R</design><brand_info>https://www.4tochki.ru/descriptions/brands/Sailun/info.html</brand_info><model_info>https://www.4tochki.ru/descriptions/models/sailun/IceBlazerAlpineEvo/info.html</model_info></item><item><status>В наличии</status><cae>3110083</cae><price_novosib3>4558</price_novosib3><price_novosib3_rozn>5325</price_novosib3_rozn><price_nvkz2>4558</price_nvkz2><price_nvkz2_rozn>5325</price_nvkz2_rozn><price_yamka>4558</price_yamka><price_yamka_rozn>5325</price_yamka_rozn><rest_novosib3>16</rest_novosib3><rest_nvkz2>16</rest_nvkz2><rest_yamka>более 40</rest_yamka><gtin>02900095882056, 04604278006625</gtin><brand>Viatti</brand><model>Strada 2 V-134</model><width>195</width><height>60</height><diameter>R15</diameter><load_index>92</load_index><speed_index>V</speed_index><season>Летняя</season><tiretype>Легковая</tiretype><diametr_out>0</diametr_out><img_small>https://api-b2b.pwrs.ru/27986/pictures/tyres/Viatti/Strada_2_V-134/src/big_0.png</img_small><name>195/60R15 92V Strada 2 V-134 TL</name><design>R</design><brand_info>https://www.4tochki.ru/descriptions/brands/viatti/info.html</brand_info></item><item><status>В наличии</status><cae>300H3033</cae><price_novosib3>9466</price_novosib3><price_novosib3_rozn>11080</price_novosib3_rozn><price_nvkz2>9466</price_nvkz2><price_nvkz2_rozn>11080</price_nvkz2_rozn><price_tomsk>9466</price_tomsk><price_tomsk_rozn>11080</price_tomsk_rozn><rest_novosib3>более 40</rest_novosib3><rest_nvkz2>4</rest_nvkz2><rest_tomsk>10</rest_tomsk><gtin>02900078197351, 06953913105130</gtin><brand>HiFly</brand><model>Win-Turi 215</model><width>265</width><height>70</height><diameter>R16</diameter><load_index>112</load_index><speed_index>T</speed_index><season>Зимняя</season><tiretype>Легковая</tiretype><diametr_out>0</diametr_out><thorn>Да</thorn><img_small>https://api-b2b.pwrs.ru/27986/pictures/tyres/HiFly/Win-Turi_215/src/big_1.png</img_small><name>265/70R16 112T Win-Turi 215 TL (шип.)</name><design>R</design><brand_info>https://www.4tochki.ru/descriptions/brands/Hifly/info.html</brand_info><model_info>https://www.4tochki.ru/descriptions/models/HiFly/WinTuri215/info.html</model_info></item><item><status>В наличии</status><cae>4137900</cae><price_novosib3>36022</price_novosib3><price_novosib3_rozn>44310</price_novosib3_rozn><rest_novosib3>4</rest_novosib3><gtin>02900078376596, 08019227413793</gtin><brand>Pirelli</brand><model>Scorpion Winter 2</model><width>255</width><height>45</height><diameter>R20</diameter><load_index>105</load_index><speed_index>V</speed_index><season>Зимняя</season><tiretype>Легковая</tiretype><diametr_out>0</diametr_out><tonnage>Да</tonnage><img_small>https://api-b2b.pwrs.ru/27986/pictures/tyres/Pirelli/Scorpion_Winter_2/src/big_0.png</img_small><name>255/45R20 105V XL Scorpion Winter 2 TL</name><design>R</design><brand_info>https://www.4tochki.ru/descriptions/brands/pirelli/info.html</brand_info><model_info>https://www.4tochki.ru/descriptions/models/pirelli/Scorpion_Winter2/info.html</model_info></item><item><status>В наличии</status><cae>CTS277542</cae><price_novosib3>8880</price_novosib3><price_novosib3_rozn>10390</price_novosib3_rozn><rest_novosib3>4</rest_novosib3><gtin>06938112616441, 02900273258604</gtin><brand>Goodride</brand><model>Sport SA-37</model><width>255</width><height>45</height><diameter>ZR18</diameter><load_index>99</load_index><speed_index>W</speed_index><season>Летняя</season><tiretype>Легковая</tiretype><diametr_out>0</diametr_out><tonnage>Да</tonnage><img_small>https://api-b2b.pwrs.ru/27986/pictures/tyres/Goodride/Sport_SA-37/src/big_0.png</img_small><name>255/45ZR18 99W XL Sport SA-37 TL</name><design>ZR</design><brand_info>https://www.4tochki.ru/descriptions/brands/Goodride/info.html</brand_info><model_info>https://www.4tochki.ru/descriptions/models/Goodride/SportSA37/info.html</model_info></item><item><status>В наличии</status><cae>AAH209U</cae><price_novosib3>7399</price_novosib3><price_novosib3_rozn>8660</price_novosib3_rozn><rest_novosib3>3</rest_novosib3><gtin>06959585852983, 02900660588062, 06959585834446, 02900241048312</gtin><brand>Antares</brand><model>SMT A7</model><width>215</width><height>75</height><diameter>R15</diameter><load_index>100/97</load_index><speed_index>S</speed_index><season>Летняя</season><tiretype>Легковая</tiretype><diametr_out>0</diametr_out><side>M+S</side><usa>LT</usa><img_small>https://api-b2b.pwrs.ru/27986/pictures/tyres/Antares/SMT_A7/src/big_0.png</img_small><name>LT215/75R15 100/97S SMT A7 TL M+S 6PR</name><design>R</design><brand_info>https://www.4tochki.ru/descriptions/brands/antares/info.html</brand_info><model_info>https://www.4tochki.ru/descriptions/models/antares/SMTA7/info.html</model_info></item><item><status>В наличии</status><cae>AB647</cae><price_novosib3>7001</price_novosib3><price_novosib3_rozn>8200</price_novosib3_rozn><rest_novosib3>8</rest_novosib3><gtin>06959585845862, 02900243397371</gtin><brand>Antares</brand><model>Majoris R1</model><width>225</width><height>55</height><diameter>R19</diameter><load_index>99</load_index><speed_index>V</speed_index><season>Летняя</season><tiretype>Легковая</tiretype><diametr_out>0</diametr_out><side>M+S</side><img_small>https://api-b2b.pwrs.ru/27986/pictures/tyres/Antares/Majoris_R1/src/big_0.png</img_small><name>225/55R19 99V Majoris R1 TL M+S</name><design>R</design><brand_info>https://www.4tochki.ru/descriptions/brands/antares/info.html</brand_info><model_info>https://www.4tochki.ru/descriptions/models/antares/MAJORIS_R1/info.html</model_info></item><item><status>В наличии</status><cae>YSTX3R1930</cae><price_novosib3>10990</price_novosib3><price_novosib3_rozn>12860</price_novosib3_rozn><rest_novosib3>4</rest_novosib3><gtin>06958460921349, 02900255251883</gtin><brand>Tracmax</brand><model>X-Privilo TX3</model><width>275</width><height>55</height><diameter>ZR19</diameter><load_index>111</load_index><speed_index>W</speed_index><season>Летняя</season><tiretype>Легковая</tiretype><diametr_out>0</diametr_out><img_small>https://api-b2b.pwrs.ru/27986/pictures/tyres/Tracmax/X-Privilo_TX3/src/big_0.png</img_small><name>275/55ZR19 111W X-Privilo TX3 TL</name><design>ZR</design><brand_info>https://www.4tochki.ru/descriptions/brands/Tracmax/info.html</brand_info><model_info>https://www.4tochki.ru/descriptions/models/Tracmax/X_PriviloTX3/info.html</model_info></item><item><status>В наличии</status><cae>AAB4106</cae><price_novosib3>6880</price_novosib3><price_novosib3_rozn>8050</price_novosib3_rozn><price_tomsk>6880</price_tomsk><price_tomsk_rozn>8050</price_tomsk_rozn><rest_novosib3>2</rest_novosib3><rest_tomsk>11</rest_tomsk><gtin>06959585844841, 02900271753347</gtin><brand>Antares</brand><model>Grip 60 ice</model><width>225</width><height>65</height><diameter>R17</diameter><load_index>102</load_index><speed_index>S</speed_index><season>Зимняя</season><tiretype>Легковая</tiretype><diametr_out>0</diametr_out><thorn>Да</thorn><img_small>https://api-b2b.pwrs.ru/27986/pictures/tyres/Antares/Grip_60_ice/src/big_1.png</img_small><name>225/65R17 102S Grip 60 ice TL (шип.)</name><design>R</design><brand_info>https://www.4tochki.ru/descriptions/brands/antares/info.html</brand_info><model_info>https://www.4tochki.ru/descriptions/models/antares/Grip60ice/info.html</model_info></item><item><status>В наличии</status><cae>YSS360R2002</cae><price_novosib3>9199</price_novosib3><price_novosib3_rozn>10770</price_novosib3_rozn><rest_novosib3>4</rest_novosib3><gtin>02900270340661, 06958460935711</gtin><brand>Tracmax</brand><model>X-Privilo S360</model><width>245</width><height>45</height><diameter>R20</diameter><load_index>103</load_index><speed_index>V</speed_index><season>Зимняя</season><tiretype>Легковая</tiretype><diametr_out>0</diametr_out><tonnage>Да</tonnage><img_small>https://api-b2b.pwrs.ru/27986/pictures/tyres/Tracmax/X-Privilo_S360/src/big_0.png</img_small><name>245/45R20 103V XL X-Privilo S360 TL</name><design>R</design><brand_info>https://www.4tochki.ru/descriptions/brands/Tracmax/info.html</brand_info><model_info>https://www.4tochki.ru/descriptions/models/Tracmax/X_PriviloS360/info.html</model_info></item><item><status>В наличии</status><cae>YSS500R2004</cae><price_novosib3>10599</price_novosib3><price_novosib3_rozn>12410</price_novosib3_rozn><price_nvkz2>10599</price_nvkz2><price_nvkz2_rozn>12410</price_nvkz2_rozn><price_tomsk>10599</price_tomsk><price_tomsk_rozn>12410</price_tomsk_rozn><price_dvdv>10599</price_dvdv><price_dvdv_rozn>12410</price_dvdv_rozn><price_yamka>10599</price_yamka><price_yamka_rozn>12410</price_yamka_rozn><rest_novosib3>более 40</rest_novosib3><rest_nvkz2>12</rest_nvkz2><rest_tomsk>24</rest_tomsk><rest_dvdv>более 40</rest_dvdv><rest_yamka>8</rest_yamka><gtin>06958460935056, 02900272438885</gtin><brand>Tracmax</brand><model>X-Privilo S500</model><width>265</width><height>50</height><diameter>R20</diameter><load_index>111</load_index><speed_index>T</speed_index><season>Зимняя</season><tiretype>Легковая</tiretype><diametr_out>0</diametr_out><thorn>Да</thorn><tonnage>Да</tonnage><img_small>https://api-b2b.pwrs.ru/27986/pictures/tyres/Tracmax/X-Privilo_S500/src/big_1.png</img_small><name>265/50R20 111T XL X-Privilo S500 TL (шип.)</name><design>R</design><brand_info>https://www.4tochki.ru/descriptions/brands/Tracmax/info.html</brand_info><model_info>https://www.4tochki.ru/descriptions/models/Tracmax/XPriviloS5000/info.html</model_info></item><item><status>В наличии</status><cae>YSSR1R1603</cae><price_novosib3>7480</price_novosib3><price_novosib3_rozn>8760</price_novosib3_rozn><rest_novosib3>8</rest_novosib3><gtin>06958460904052, 02900278006101</gtin><brand>Tracmax</brand><model>Ice-Plus SR1</model><width>215</width><height>65</height><diameter>R16C</diameter><load_index>109/107</load_index><speed_index>Q</speed_index><season>Зимняя</season><tiretype>Легковая</tiretype><diametr_out>0</diametr_out><thorn>Да</thorn><reinforced>Да</reinforced><img_small>https://api-b2b.pwrs.ru/27986/pictures/tyres/Tracmax/Ice-Plus_SR1/src/big_1.png</img_small><name>215/65R16C 109/107Q Ice-Plus SR1 TL 8PR (шип.)</name><design>R</design><brand_info>https://www.4tochki.ru/descriptions/brands/Tracmax/info.html</brand_info><model_info>https://www.4tochki.ru/descriptions/models/Tracmax/IcePlusSR1/info.html</model_info></item><item><status>В наличии</status><cae>JSGS14</cae><price_novosib3>6480</price_novosib3><price_novosib3_rozn>7590</price_novosib3_rozn><price_tomsk>6480</price_tomsk><price_tomsk_rozn>7590</price_tomsk_rozn><rest_novosib3>1</rest_novosib3><rest_tomsk>2</rest_tomsk><gtin>02900257615508, 06974610321500</gtin><brand>Landspider</brand><model>Wildtraxx AT II</model><width>185</width><height>75</height><diameter>R16C</diameter><load_index>104/102</load_index><speed_index>R</speed_index><season>Летняя</season><tiretype>Легковая</tiretype><diametr_out>0</diametr_out><reinforced>Да</reinforced><img_small>https://api-b2b.pwrs.ru/27986/pictures/tyres/Landspider/Wildtraxx_AT_II/src/big_0.png</img_small><name>185/75R16C 104/102R Wildtraxx AT II TL BSW</name><design>R</design><brand_info>https://www.4tochki.ru/descriptions/brands/Landspider/info.html</brand_info><model_info>https://www.4tochki.ru/descriptions/models/landspider/WildtraxxAT_II/info.html</model_info></item><item><status>В наличии</status><cae>AAB545U</cae><price_novosib3>6780</price_novosib3><price_novosib3_rozn>7940</price_novosib3_rozn><price_yamka>6780</price_yamka><price_yamka_rozn>7940</price_yamka_rozn><rest_novosib3>4</rest_novosib3><rest_yamka>1</rest_yamka><gtin>02900278922449, 06959585834699</gtin><brand>Antares</brand><model>Comfort A5</model><width>225</width><height>50</height><diameter>R18</diameter><load_index>95</load_index><speed_index>V</speed_index><season>Летняя</season><tiretype>Легковая</tiretype><diametr_out>0</diametr_out><side>M+S</side><img_small>https://api-b2b.pwrs.ru/27986/pictures/tyres/Antares/Comfort_A5/src/big_0.png</img_small><name>225/50R18 95V Comfort A5 TL M+S</name><design>R</design><brand_info>https://www.4tochki.ru/descriptions/brands/antares/info.html</brand_info><model_info>https://www.4tochki.ru/descriptions/models/antares/ComfortA5/info.html</model_info></item><item><status>В наличии</status><cae>BGP018</cae><price_novosib3>7780</price_novosib3><price_novosib3_rozn>9110</price_novosib3_rozn><rest_novosib3>16</rest_novosib3><gtin>00840156425414</gtin><brand>Landspider</brand><model>Citytraxx H/P</model><width>235</width><height>55</height><diameter>ZR18</diameter><load_index>104</load_index><speed_index>W</speed_index><season>Летняя</season><tiretype>Легковая</tiretype><diametr_out>0</diametr_out><tonnage>Да</tonnage><img_small>https://api-b2b.pwrs.ru/27986/pictures/tyres/Landspider/Citytraxx_H_P/src/big_0.png</img_small><name>235/55ZR18 104W XL Citytraxx H/P TL BSW</name><design>ZR</design><brand_info>https://www.4tochki.ru/descriptions/brands/Landspider/info.html</brand_info><model_info>https://www.4tochki.ru/descriptions/models/landspider/CitytraxxHP/info.html</model_info></item><item><status>В наличии</status><cae>AB6011U</cae><price_novosib3>8250</price_novosib3><price_novosib3_rozn>9660</price_novosib3_rozn><rest_novosib3>4</rest_novosib3><gtin>06959585830059</gtin><brand>Antares</brand><model>Ingens A1</model><width>255</width><height>45</height><diameter>ZR19</diameter><load_index>104</load_index><speed_index>W</speed_index><season>Летняя</season><tiretype>Легковая</tiretype><diametr_out>0</diametr_out><tonnage>Да</tonnage><side>M+S</side><img_small>https://api-b2b.pwrs.ru/27986/pictures/tyres/Antares/Ingens_A1/src/big_0.png</img_small><name>255/45ZR19 104W XL Ingens A1 TL M+S</name><design>ZR</design><brand_info>https://www.4tochki.ru/descriptions/brands/antares/info.html</brand_info><model_info>https://www.4tochki.ru/descriptions/models/antares/IngensA1/info.html</model_info></item><item><status>В наличии</status><cae>T732323</cae><price_novosib3>4112</price_novosib3><price_novosib3_rozn>5140</price_novosib3_rozn><price_nvkz2>4112</price_nvkz2><price_nvkz2_rozn>5140</price_nvkz2_rozn><price_tomsk>4112</price_tomsk><price_tomsk_rozn>5140</price_tomsk_rozn><rest_novosib3>13</rest_novosib3><rest_nvkz2>4</rest_nvkz2><rest_tomsk>4</rest_tomsk><gtin>04620200349868, 02900357995807</gtin><brand>Ikon Tyres</brand><model>Nordman SX3</model><width>195</width><height>50</height><diameter>R15</diameter><load_index>82</load_index><speed_index>H</speed_index><season>Летняя</season><tiretype>Легковая</tiretype><diametr_out>0</diametr_out><img_small>https://api-b2b.pwrs.ru/27986/pictures/tyres/Ikon_Tyres/Nordman_SX3/src/big_0.png</img_small><name>195/50R15 82H Nordman SX3 TL</name><design>R</design><brand_info>https://www.4tochki.ru/descriptions/brands/ikon/info.html</brand_info><model_info>https://www.4tochki.ru/descriptions/models/Ikon_tyres/Nordman_SX3/info.html</model_info></item><item><status>В наличии</status><cae>T731446</cae><price_novosib3>4746</price_novosib3><price_novosib3_rozn>5940</price_novosib3_rozn><price_nvkz2>4746</price_nvkz2><price_nvkz2_rozn>5940</price_nvkz2_rozn><rest_novosib3>4</rest_novosib3><rest_nvkz2>4</rest_nvkz2><gtin>02900302284956, 04620200347888</gtin><brand>Ikon Tyres</brand><model>Autograph Eco 3</model><width>185</width><height>65</height><diameter>R14</diameter><load_index>86</load_index><speed_index>H</speed_index><season>Летняя</season><tiretype>Легковая</tiretype><diametr_out>0</diametr_out><img_small>https://api-b2b.pwrs.ru/27986/pictures/tyres/Ikon_Tyres/Autograph_Eco_3/src/big_0.png</img_small><name>185/65R14 86H Autograph Eco 3 TL</name><design>R</design><brand_info>https://www.4tochki.ru/descriptions/brands/ikon/info.html</brand_info><model_info>https://www.4tochki.ru/descriptions/models/Ikon_tyres/Autograph_Eco_3/info.html</model_info></item><item><status>В наличии</status><cae>T730549</cae><price_novosib3>9780</price_novosib3><price_novosib3_rozn>12230</price_novosib3_rozn><rest_novosib3>8</rest_novosib3><gtin>02900288852644, 02900826325968, 04620200346010</gtin><brand>Ikon Tyres</brand><model>Autograph Ultra 2</model><width>225</width><height>40</height><diameter>ZR18</diameter><load_index>92</load_index><speed_index>Y</speed_index><season>Летняя</season><tiretype>Легковая</tiretype><diametr_out>0</diametr_out><tonnage>Да</tonnage><img_small>https://api-b2b.pwrs.ru/27986/pictures/tyres/Ikon_Tyres/Autograph_Ultra_2/src/big_0.png</img_small><name>225/40ZR18 92Y XL Autograph Ultra 2 TL</name><design>ZR</design><brand_info>https://www.4tochki.ru/descriptions/brands/ikon/info.html</brand_info><model_info>https://www.4tochki.ru/descriptions/models/Ikon_tyres/Autograph_Ultra_2/info.html</model_info></item><item><status>В наличии</status><cae>AB4314</cae><price_novosib3>4790</price_novosib3><price_novosib3_rozn>5610</price_novosib3_rozn><price_nvkz2>4790</price_nvkz2><price_nvkz2_rozn>5610</price_nvkz2_rozn><price_tomsk>4790</price_tomsk><price_tomsk_rozn>5610</price_tomsk_rozn><rest_novosib3>2</rest_novosib3><rest_nvkz2>8</rest_nvkz2><rest_tomsk>8</rest_tomsk><gtin>06959585856905</gtin><brand>Antares</brand><model>Ingens EV</model><width>215</width><height>50</height><diameter>R17</diameter><load_index>95</load_index><speed_index>V</speed_index><season>Летняя</season><tiretype>Легковая</tiretype><diametr_out>0</diametr_out><tonnage>Да</tonnage><img_small>https://api-b2b.pwrs.ru/27986/pictures/tyres/Antares/Ingens_EV/src/big_0.png</img_small><name>215/50R17 95V XL Ingens EV TL</name><design>R</design><brand_info>https://www.4tochki.ru/descriptions/brands/antares/info.html</brand_info><model_info>https://www.4tochki.ru/descriptions/models/antares/IngensEV/info.html</model_info></item><item><status>В наличии</status><cae>04242010000</cae><price_novosib3>9140</price_novosib3><price_novosib3_rozn>10970</price_novosib3_rozn><price_nvkz2>9140</price_nvkz2><price_nvkz2_rozn>10970</price_nvkz2_rozn><price_tomsk>9140</price_tomsk><price_tomsk_rozn>10970</price_tomsk_rozn><rest_novosib3>4</rest_novosib3><rest_nvkz2>6</rest_nvkz2><rest_tomsk>4</rest_tomsk><gtin>04680197181780, 02900306745026</gtin><brand>Torero</brand><model>MPS 125 Variant All Weather</model><width>195</width><height>75</height><diameter>R16C</diameter><load_index>107/105</load_index><speed_index>R</speed_index><season>Всесезонная</season><tiretype>Легковая</tiretype><diametr_out>0</diametr_out><reinforced>Да</reinforced><img_small>https://api-b2b.pwrs.ru/27986/pictures/tyres/Torero/MPS_125_Variant_All_Weather/src/big_04242000000.png</img_small><name>195/75R16C 107/105R MPS 125 Variant All Weather TL</name><design>R</design><brand_info>https://www.4tochki.ru/descriptions/brands/Torero/info.html</brand_info></item><item><status>В наличии</status><cae>T729920</cae><price_novosib3>5846</price_novosib3><price_novosib3_rozn>7200</price_novosib3_rozn><price_nvkz2>5846</price_nvkz2><price_nvkz2_rozn>7200</price_nvkz2_rozn><rest_novosib3>14</rest_novosib3><rest_nvkz2>8</rest_nvkz2><gtin>04620200344313, 02900618677329</gtin><brand>Ikon Tyres</brand><model>Nordman RS2</model><width>185</width><height>55</height><diameter>R15</diameter><load_index>86</load_index><speed_index>R</speed_index><season>Зимняя</season><tiretype>Легковая</tiretype><diametr_out>0</diametr_out><tonnage>Да</tonnage><img_small>https://api-b2b.pwrs.ru/27986/pictures/tyres/Ikon_Tyres/Nordman_RS2/src/big_0.png</img_small><name>185/55R15 86R XL Nordman RS2 TL</name><design>R</design><brand_info>https://www.4tochki.ru/descriptions/brands/ikon/info.html</brand_info><model_info>https://www.4tochki.ru/descriptions/models/Ikon_tyres/Nordman_RS2/info.html</model_info></item><item><status>В наличии</status><cae>T730676</cae><price_novosib3>14467</price_novosib3><price_novosib3_rozn>17800</price_novosib3_rozn><price_nvkz2>14467</price_nvkz2><price_nvkz2_rozn>17800</price_nvkz2_rozn><price_tomsk>14467</price_tomsk><price_tomsk_rozn>17800</price_tomsk_rozn><price_yamka>14467</price_yamka><price_yamka_rozn>17800</price_yamka_rozn><rest_novosib3>более 40</rest_novosib3><rest_nvkz2>4</rest_nvkz2><rest_tomsk>8</rest_tomsk><rest_yamka>более 40</rest_yamka><gtin>02900826727618, 04620200346843</gtin><brand>Ikon Tyres</brand><model>Autograph Snow 3 SUV</model><width>225</width><height>55</height><diameter>R19</diameter><load_index>103</load_index><speed_index>R</speed_index><season>Зимняя</season><tiretype>Легковая</tiretype><diametr_out>0</diametr_out><tonnage>Да</tonnage><img_small>https://api-b2b.pwrs.ru/27986/pictures/tyres/Ikon_Tyres/Autograph_Snow_3_SUV/src/big_0.png</img_small><name>225/55R19 103R XL Autograph Snow 3 SUV TL</name><design>R</design><brand_info>https://www.4tochki.ru/descriptions/brands/ikon/info.html</brand_info><model_info>https://www.4tochki.ru/descriptions/models/Ikon_tyres/Autograph_Snow3_SUV/info.html</model_info></item><item><status>В наличии</status><cae>T730769</cae><price_novosib3>12252</price_novosib3><price_novosib3_rozn>15070</price_novosib3_rozn><price_nvkz2>12252</price_nvkz2><price_nvkz2_rozn>15070</price_nvkz2_rozn><price_tomsk>12252</price_tomsk><price_tomsk_rozn>15070</price_tomsk_rozn><price_dvdv>12252</price_dvdv><price_dvdv_rozn>15070</price_dvdv_rozn><price_yamka>12252</price_yamka><price_yamka_rozn>15070</price_yamka_rozn><rest_novosib3>более 40</rest_novosib3><rest_nvkz2>16</rest_nvkz2><rest_tomsk>20</rest_tomsk><rest_dvdv>более 40</rest_dvdv><rest_yamka>более 40</rest_yamka><gtin>04620200347284, 02900413801301</gtin><brand>Ikon Tyres</brand><model>Autograph Snow 3 SUV</model><width>215</width><height>55</height><diameter>R18</diameter><load_index>99</load_index><speed_index>R</speed_index><season>Зимняя</season><tiretype>Легковая</tiretype><diametr_out>0</diametr_out><tonnage>Да</tonnage><img_small>https://api-b2b.pwrs.ru/27986/pictures/tyres/Ikon_Tyres/Autograph_Snow_3_SUV/src/big_0.png</img_small><name>215/55R18 99R XL Autograph Snow 3 SUV TL</name><design>R</design><brand_info>https://www.4tochki.ru/descriptions/brands/ikon/info.html</brand_info><model_info>https://www.4tochki.ru/descriptions/models/Ikon_tyres/Autograph_Snow3_SUV/info.html</model_info></item><item><status>В наличии</status><cae>TS72186</cae><price_novosib3>11177</price_novosib3><price_novosib3_rozn>13750</price_novosib3_rozn><price_nvkz2>11177</price_nvkz2><price_nvkz2_rozn>13750</price_nvkz2_rozn><price_tomsk>11177</price_tomsk><price_tomsk_rozn>13750</price_tomsk_rozn><price_yamka>11177</price_yamka><price_yamka_rozn>13750</price_yamka_rozn><rest_novosib3>более 40</rest_novosib3><rest_nvkz2>8</rest_nvkz2><rest_tomsk>15</rest_tomsk><rest_yamka>более 40</rest_yamka><gtin>02900303937158, 04620200344566</gtin><brand>Ikon Tyres</brand><model>Nordman 7 SUV</model><width>245</width><height>70</height><diameter>R16</diameter><load_index>111</load_index><speed_index>T</speed_index><season>Зимняя</season><tiretype>Легковая</tiretype><diametr_out>0</diametr_out><thorn>Да</thorn><tonnage>Да</tonnage><img_small>https://api-b2b.pwrs.ru/27986/pictures/tyres/Ikon_Tyres/Nordman_7_SUV/src/big_1.png</img_small><name>245/70R16 111T XL Nordman 7 SUV TL (шип.)</name><design>R</design><brand_info>https://www.4tochki.ru/descriptions/brands/ikon/info.html</brand_info><model_info>https://www.4tochki.ru/descriptions/models/Ikon_tyres/Nordman7_SUV/info.html</model_info></item><item><status>В наличии</status><cae>TS72204</cae><price_novosib3>8263</price_novosib3><price_novosib3_rozn>10170</price_novosib3_rozn><price_nvkz2>8263</price_nvkz2><price_nvkz2_rozn>10170</price_nvkz2_rozn><price_tomsk>8263</price_tomsk><price_tomsk_rozn>10170</price_tomsk_rozn><price_yamka>8263</price_yamka><price_yamka_rozn>10170</price_yamka_rozn><rest_novosib3>более 40</rest_novosib3><rest_nvkz2>26</rest_nvkz2><rest_tomsk>12</rest_tomsk><rest_yamka>более 40</rest_yamka><gtin>02900578794883, 04620200344740</gtin><brand>Ikon Tyres</brand><model>Autograph Ice 9</model><width>205</width><height>55</height><diameter>R16</diameter><load_index>94</load_index><speed_index>T</speed_index><season>Зимняя</season><tiretype>Легковая</tiretype><diametr_out>0</diametr_out><thorn>Да</thorn><tonnage>Да</tonnage><img_small>https://api-b2b.pwrs.ru/27986/pictures/tyres/Ikon_Tyres/Autograph_Ice_9/src/big_1.png</img_small><name>205/55R16 94T XL Autograph Ice 9 TL (шип.)</name><design>R</design><brand_info>https://www.4tochki.ru/descriptions/brands/ikon/info.html</brand_info><model_info>https://www.4tochki.ru/descriptions/models/Ikon_tyres/Autograph_Ice9/info.html</model_info></item><item><status>В наличии</status><cae>TS72245</cae><price_novosib3>14826</price_novosib3><price_novosib3_rozn>18240</price_novosib3_rozn><price_tomsk>14826</price_tomsk><price_tomsk_rozn>18240</price_tomsk_rozn><price_yamka>14826</price_yamka><price_yamka_rozn>18240</price_yamka_rozn><rest_novosib3>24</rest_novosib3><rest_tomsk>8</rest_tomsk><rest_yamka>24</rest_yamka><gtin>02900609301929, 02900609341956, 02900609352730, 02900609357827, 04620200345044</gtin><brand>Ikon Tyres</brand><model>Autograph Ice 9 SUV</model><width>215</width><height>60</height><diameter>R17</diameter><load_index>100</load_index><speed_index>T</speed_index><season>Зимняя</season><tiretype>Легковая</tiretype><diametr_out>0</diametr_out><thorn>Да</thorn><tonnage>Да</tonnage><img_small>https://api-b2b.pwrs.ru/27986/pictures/tyres/Ikon_Tyres/Autograph_Ice_9_SUV/src/big_1.png</img_small><name>215/60R17 100T XL Autograph Ice 9 SUV TL (шип.)</name><design>R</design><brand_info>https://www.4tochki.ru/descriptions/brands/ikon/info.html</brand_info><model_info>https://www.4tochki.ru/descriptions/models/Ikon_tyres/Autograph_Ice9_SUV/info.html</model_info></item><item><status>В наличии</status><cae>4463800</cae><price_novosib3>7963</price_novosib3><price_novosib3_rozn>9800</price_novosib3_rozn><price_yamka>7963</price_yamka><price_yamka_rozn>9800</price_yamka_rozn><rest_novosib3>20</rest_novosib3><rest_yamka>более 40</rest_yamka><gtin>08019227446388</gtin><brand>Pirelli Formula</brand><model>Ice FR</model><width>225</width><height>55</height><diameter>R18</diameter><load_index>102</load_index><speed_index>H</speed_index><season>Зимняя</season><tiretype>Легковая</tiretype><diametr_out>0</diametr_out><tonnage>Да</tonnage><img_small>https://api-b2b.pwrs.ru/27986/pictures/tyres/Formula/Formula_Ice_Friction/src/big_0.png</img_small><name>225/55R18 102H XL Ice FR TL</name><design>R</design><brand_info>https://www.4tochki.ru/descriptions/brands/pirelli/info.html</brand_info><model_info>https://www.4tochki.ru/descriptions/models/pirelli/Formula_IceFR/info.html</model_info></item><item><status>В наличии</status><cae>GTA/T009</cae><price_novosib3>7880</price_novosib3><price_novosib3_rozn>9220</price_novosib3_rozn><rest_novosib3>4</rest_novosib3><gtin>06974610328523</gtin><brand>Landspider</brand><model>Grandtraxx A/T</model><width>245</width><height>65</height><diameter>R17</diameter><load_index>111</load_index><speed_index>H</speed_index><season>Всесезонная</season><tiretype>Легковая</tiretype><diametr_out>0</diametr_out><tonnage>Да</tonnage><img_small>https://api-b2b.pwrs.ru/27986/pictures/tyres/Landspider/Grandtraxx_A_T/src/big_0.png</img_small><name>245/65R17 111H XL Grandtraxx A/T TL 4PR</name><design>R</design><brand_info>https://www.4tochki.ru/descriptions/brands/Landspider/info.html</brand_info><model_info>https://www.4tochki.ru/descriptions/models/landspider/Grandtraxx_AT/info.html</model_info></item><item><status>В наличии</status><cae>R9090</cae><price_novosib3>11980</price_novosib3><price_novosib3_rozn>14940</price_novosib3_rozn><rest_novosib3>4</rest_novosib3><gtin>04548515307598</gtin><brand>Yokohama</brand><model>Advan dB V553</model><width>225</width><height>55</height><diameter>R17</diameter><load_index>97</load_index><speed_index>W</speed_index><season>Летняя</season><tiretype>Легковая</tiretype><diametr_out>0</diametr_out><img_small>https://api-b2b.pwrs.ru/27986/pictures/tyres/Yokohama/Advan_dB_V553/src/big_0.png</img_small><name>225/55R17 97W Advan dB V553 TL</name><design>R</design><brand_info>https://www.4tochki.ru/descriptions/brands/yokohama/info.html</brand_info></item><item><status>В наличии</status><cae>TS78057</cae><price_novosib3>7464</price_novosib3><price_novosib3_rozn>9190</price_novosib3_rozn><price_yamka>7464</price_yamka><price_yamka_rozn>9190</price_yamka_rozn><rest_novosib3>4</rest_novosib3><rest_yamka>24</rest_yamka><gtin>02901024195988, 04680617435998</gtin><brand>Ikon Tyres</brand><model>Character Ice 8</model><width>205</width><height>70</height><diameter>R15</diameter><load_index>100</load_index><speed_index>T</speed_index><season>Зимняя</season><tiretype>Легковая</tiretype><diametr_out>0</diametr_out><thorn>Да</thorn><tonnage>Да</tonnage><img_small>https://api-b2b.pwrs.ru/27986/pictures/tyres/Ikon_Tyres/Character_Ice_8/src/big_1.png</img_small><name>205/70R15 100T XL Character Ice 8 TL (шип.)</name><design>R</design><brand_info>https://www.4tochki.ru/descriptions/brands/ikon/info.html</brand_info><model_info>https://www.4tochki.ru/descriptions/models/Ikon_tyres/Character_Ice_8/info.html</model_info></item></items>